geogear/__init__.py
geogear/backend.py
geogear/functions.py
geogear/.git/COMMIT_EDITMSG
geogear/.git/FETCH_HEAD
geogear/.git/HEAD
geogear/.git/config
geogear/.git/description
geogear/.git/index
geogear/.git/hooks/applypatch-msg.sample
geogear/.git/hooks/commit-msg.sample
geogear/.git/hooks/fsmonitor-watchman.sample
geogear/.git/hooks/post-update.sample
geogear/.git/hooks/pre-applypatch.sample
geogear/.git/hooks/pre-commit.sample
geogear/.git/hooks/pre-merge-commit.sample
geogear/.git/hooks/pre-push.sample
geogear/.git/hooks/pre-rebase.sample
geogear/.git/hooks/pre-receive.sample
geogear/.git/hooks/prepare-commit-msg.sample
geogear/.git/hooks/push-to-checkout.sample
geogear/.git/hooks/update.sample
geogear/.git/info/exclude
geogear/.git/logs/refs/remotes/origin/main
geogear/.git/objects/02/2934a8442187685768ea6d5a11f253c2fd7679
geogear/.git/objects/0c/b5f2a1f502e79863732c5408d1c4837bbc6187
geogear/.git/objects/15/ea83f855dd528406af9dc9a5b0df3bac3d3bfe
geogear/.git/objects/27/5f5b9394cca6f938edfb3301cc42b9166ff865
geogear/.git/objects/2a/b31dd019f07e1c6655971f9a2516b0df7f7756
geogear/.git/objects/3b/077194bc4dc8d73f49b22256d004989a61ea90
geogear/.git/objects/4c/155b41ce32bfe48b956e28419bc2f631253994
geogear/.git/objects/4c/3832725f2bb5e9a2be89e62ddcbb97bba97749
geogear/.git/objects/4d/f30555d5a2a689cb937c148f4aade664eb05d5
geogear/.git/objects/51/7cd72dac22abe8c860811e90949c7a2400e9e0
geogear/.git/objects/59/feee15e5f941900dfd57c99059fabce9660dca
geogear/.git/objects/5b/4f61c17fc03351f69d58caf45c2b0be7d96890
geogear/.git/objects/6b/17534a0320c5627212885f03fe81eb7b2378f5
geogear/.git/objects/6d/aa4da759edeb4fc7013d56cf2d98a73fcdcf1f
geogear/.git/objects/74/f65fd4b6d319faed8ba121ab2cfdeb4a0b7bb6
geogear/.git/objects/82/f613ad689858b6073bb501fbce72351c7ba872
geogear/.git/objects/89/c490b54ea0f87435ea6e2d50b2dd717dab6557
geogear/.git/objects/8b/46ff13be029cf54d88127c98348e8c1e79a695
geogear/.git/objects/a9/029352cb68c23745dd19c77ad9460f41a212f8
geogear-1.0.dist-info/WHEEL
geogear-1.0.dist-info/METADATA
geogear-1.0.dist-info/RECORD
